r3dis/__init__.py
r3dis/__main__.py
r3dis/resp.py
r3dis/server.py
r3dis-0.0.4.dist-info/LICENSE
r3dis-0.0.4.dist-info/METADATA
r3dis-0.0.4.dist-info/WHEEL
r3dis-0.0.4.dist-info/RECORD
